helpertools/__init__.py
helpertools/__main__.py
helpertools/cli.py
helpertools/convert.py
helpertools/decorators.py
helpertools/filereader.py
helpertools/http.py
helpertools/prettyprint.py
helpertools/testgenerator.py
helpertools/webscrap.py
helpertools-1.0.3.dist-info/AUTHORS.rst
helpertools-1.0.3.dist-info/LICENSE
helpertools-1.0.3.dist-info/METADATA
helpertools-1.0.3.dist-info/WHEEL
helpertools-1.0.3.dist-info/entry_points.txt
helpertools-1.0.3.dist-info/top_level.txt
helpertools-1.0.3.dist-info/RECORD
