Metadata-Version: 2.1
Name: helpertools
Version: 1.0.3
Summary: helper tools for python 
Home-page: https://github.com/helpertools/helpertools
Author: sandeep SN
Author-email: sandeepsn1997@gmail.com
License: Apache-2.0
Project-URL: Documentation, https://helpertools.readthedocs.io/
Project-URL: Changelog, https://helpertools.readthedocs.io/en/latest/changelog.html
Project-URL: Issue Tracker, https://github.com/helpertools/helpertools/issues
Platform: UNKNOWN
Classifier: Development Status :: 5 - Production/Stable
Classifier: Intended Audience :: Developers
Classifier: License :: OSI Approved :: Apache Software License
Classifier: Operating System :: Unix
Classifier: Operating System :: POSIX
Classifier: Operating System :: Microsoft :: Windows
Classifier: Programming Language :: Python
Classifier: Programming Language :: Python :: 2.7
Classifier: Programming Language :: Python :: 3
Classifier: Programming Language :: Python :: 3.5
Classifier: Programming Language :: Python :: 3.6
Classifier: Programming Language :: Python :: 3.7
Classifier: Programming Language :: Python :: 3.8
Classifier: Programming Language :: Python :: Implementation :: CPython
Classifier: Programming Language :: Python :: Implementation :: PyPy
Classifier: Topic :: Utilities
Requires-Python: >=2.7, !=3.0.*, !=3.1.*, !=3.2.*, !=3.3.*, !=3.4.*
